{
    "abilities": [{
        "name": "tangled-feet",
        "url": "https://pokeapi.co/api/v2/ability/77/"
    }, {
        "name": "motor-drive",
        "url": "https://pokeapi.co/api/v2/ability/78/"
    }, {
        "name": "rivalry",
        "url": "https://pokeapi.co/api/v2/ability/79/"
    }, {
        "name": "steadfast",
        "url": "https://pokeapi.co/api/v2/ability/80/"
    }, {
        "name": "snow-cloak",
        "url": "https://pokeapi.co/api/v2/ability/81/"
    }, {
        "name": "gluttony",
        "url": "https://pokeapi.co/api/v2/ability/82/"
    }, {
        "name": "anger-point",
        "url": "https://pokeapi.co/api/v2/ability/83/"
    }, {
        "name": "unburden",
        "url": "https://pokeapi.co/api/v2/ability/84/"
    }, {
        "name": "heatproof",
        "url": "https://pokeapi.co/api/v2/ability/85/"
    }, {
        "name": "simple",
        "url": "https://pokeapi.co/api/v2/ability/86/"
    }, {
        "name": "dry-skin",
        "url": "https://pokeapi.co/api/v2/ability/87/"
    }, {
        "name": "download",
        "url": "https://pokeapi.co/api/v2/ability/88/"
    }, {
        "name": "iron-fist",
        "url": "https://pokeapi.co/api/v2/ability/89/"
    }, {
        "name": "poison-heal",
        "url": "https://pokeapi.co/api/v2/ability/90/"
    }, {
        "name": "adaptability",
        "url": "https://pokeapi.co/api/v2/ability/91/"
    }, {
        "name": "skill-link",
        "url": "https://pokeapi.co/api/v2/ability/92/"
    }, {
        "name": "hydration",
        "url": "https://pokeapi.co/api/v2/ability/93/"
    }, {
        "name": "solar-power",
        "url": "https://pokeapi.co/api/v2/ability/94/"
    }, {
        "name": "quick-feet",
        "url": "https://pokeapi.co/api/v2/ability/95/"
    }, {
        "name": "normalize",
        "url": "https://pokeapi.co/api/v2/ability/96/"
    }, {
        "name": "sniper",
        "url": "https://pokeapi.co/api/v2/ability/97/"
    }, {
        "name": "magic-guard",
        "url": "https://pokeapi.co/api/v2/ability/98/"
    }, {
        "name": "no-guard",
        "url": "https://pokeapi.co/api/v2/ability/99/"
    }, {
        "name": "stall",
        "url": "https://pokeapi.co/api/v2/ability/100/"
    }, {
        "name": "technician",
        "url": "https://pokeapi.co/api/v2/ability/101/"
    }, {
        "name": "leaf-guard",
        "url": "https://pokeapi.co/api/v2/ability/102/"
    }, {
        "name": "klutz",
        "url": "https://pokeapi.co/api/v2/ability/103/"
    }, {
        "name": "mold-breaker",
        "url": "https://pokeapi.co/api/v2/ability/104/"
    }, {
        "name": "super-luck",
        "url": "https://pokeapi.co/api/v2/ability/105/"
    }, {
        "name": "aftermath",
        "url": "https://pokeapi.co/api/v2/ability/106/"
    }, {
        "name": "anticipation",
        "url": "https://pokeapi.co/api/v2/ability/107/"
    }, {
        "name": "forewarn",
        "url": "https://pokeapi.co/api/v2/ability/108/"
    }, {
        "name": "unaware",
        "url": "https://pokeapi.co/api/v2/ability/109/"
    }, {
        "name": "tinted-lens",
        "url": "https://pokeapi.co/api/v2/ability/110/"
    }, {
        "name": "filter",
        "url": "https://pokeapi.co/api/v2/ability/111/"
    }, {
        "name": "slow-start",
        "url": "https://pokeapi.co/api/v2/ability/112/"
    }, {
        "name": "scrappy",
        "url": "https://pokeapi.co/api/v2/ability/113/"
    }, {
        "name": "storm-drain",
        "url": "https://pokeapi.co/api/v2/ability/114/"
    }, {
        "name": "ice-body",
        "url": "https://pokeapi.co/api/v2/ability/115/"
    }, {
        "name": "solid-rock",
        "url": "https://pokeapi.co/api/v2/ability/116/"
    }, {
        "name": "snow-warning",
        "url": "https://pokeapi.co/api/v2/ability/117/"
    }, {
        "name": "honey-gather",
        "url": "https://pokeapi.co/api/v2/ability/118/"
    }, {
        "name": "frisk",
        "url": "https://pokeapi.co/api/v2/ability/119/"
    }, {
        "name": "reckless",
        "url": "https://pokeapi.co/api/v2/ability/120/"
    }, {
        "name": "multitype",
        "url": "https://pokeapi.co/api/v2/ability/121/"
    }, {
        "name": "flower-gift",
        "url": "https://pokeapi.co/api/v2/ability/122/"
    }, {
        "name": "bad-dreams",
        "url": "https://pokeapi.co/api/v2/ability/123/"
    }],
    "id": 4,
    "main_region": {
        "name": "sinnoh",
        "url": "https://pokeapi.co/api/v2/region/4/"
    },
    "moves": [{
        "name": "roost",
        "url": "https://pokeapi.co/api/v2/move/355/"
    }, {
        "name": "gravity",
        "url": "https://pokeapi.co/api/v2/move/356/"
    }, {
        "name": "miracle-eye",
        "url": "https://pokeapi.co/api/v2/move/357/"
    }, {
        "name": "wake-up-slap",
        "url": "https://pokeapi.co/api/v2/move/358/"
    }, {
        "name": "hammer-arm",
        "url": "https://pokeapi.co/api/v2/move/359/"
    }, {
        "name": "gyro-ball",
        "url": "https://pokeapi.co/api/v2/move/360/"
    }, {
        "name": "healing-wish",
        "url": "https://pokeapi.co/api/v2/move/361/"
    }, {
        "name": "brine",
        "url": "https://pokeapi.co/api/v2/move/362/"
    }, {
        "name": "natural-gift",
        "url": "https://pokeapi.co/api/v2/move/363/"
    }, {
        "name": "feint",
        "url": "https://pokeapi.co/api/v2/move/364/"
    }, {
        "name": "pluck",
        "url": "https://pokeapi.co/api/v2/move/365/"
    }, {
        "name": "tailwind",
        "url": "https://pokeapi.co/api/v2/move/366/"
    }, {
        "name": "acupressure",
        "url": "https://pokeapi.co/api/v2/move/367/"
    }, {
        "name": "metal-burst",
        "url": "https://pokeapi.co/api/v2/move/368/"
    }, {
        "name": "u-turn",
        "url": "https://pokeapi.co/api/v2/move/369/"
    }, {
        "name": "close-combat",
        "url": "https://pokeapi.co/api/v2/move/370/"
    }, {
        "name": "payback",
        "url": "https://pokeapi.co/api/v2/move/371/"
    }, {
        "name": "assurance",
        "url": "https://pokeapi.co/api/v2/move/372/"
    }, {
        "name": "embargo",
        "url": "https://pokeapi.co/api/v2/move/373/"
    }, {
        "name": "fling",
        "url": "https://pokeapi.co/api/v2/move/374/"
    }, {
        "name": "psycho-shift",
        "url": "https://pokeapi.co/api/v2/move/375/"
    }, {
        "name": "trump-card",
        "url": "https://pokeapi.co/api/v2/move/376/"
    }, {
        "name": "heal-block",
        "url": "https://pokeapi.co/api/v2/move/377/"
    }, {
        "name": "wring-out",
        "url": "https://pokeapi.co/api/v2/move/378/"
    }, {
        "name": "power-trick",
        "url": "https://pokeapi.co/api/v2/move/379/"
    }, {
        "name": "gastro-acid",
        "url": "https://pokeapi.co/api/v2/move/380/"
    }, {
        "name": "lucky-chant",
        "url": "https://pokeapi.co/api/v2/move/381/"
    }, {
        "name": "me-first",
        "url": "https://pokeapi.co/api/v2/move/382/"
    }, {
        "name": "copycat",
        "url": "https://pokeapi.co/api/v2/move/383/"
    }, {
        "name": "power-swap",
        "url": "https://pokeapi.co/api/v2/move/384/"
    }, {
        "name": "guard-swap",
        "url": "https://pokeapi.co/api/v2/move/385/"
    }, {
        "name": "punishment",
        "url": "https://pokeapi.co/api/v2/move/386/"
    }, {
        "name": "last-resort",
        "url": "https://pokeapi.co/api/v2/move/387/"
    }, {
        "name": "worry-seed",
        "url": "https://pokeapi.co/api/v2/move/388/"
    }, {
        "name": "sucker-punch",
        "url": "https://pokeapi.co/api/v2/move/389/"
    }, {
        "name": "toxic-spikes",
        "url": "https://pokeapi.co/api/v2/move/390/"
    }, {
        "name": "heart-swap",
        "url": "https://pokeapi.co/api/v2/move/391/"
    }, {
        "name": "aqua-ring",
        "url": "https://pokeapi.co/api/v2/move/392/"
    }, {
        "name": "magnet-rise",
        "url": "https://pokeapi.co/api/v2/move/393/"
    }, {
        "name": "flare-blitz",
        "url": "https://pokeapi.co/api/v2/move/394/"
    }, {
        "name": "force-palm",
        "url": "https://pokeapi.co/api/v2/move/395/"
    }, {
        "name": "aura-sphere",
        "url": "https://pokeapi.co/api/v2/move/396/"
    }, {
        "name": "rock-polish",
        "url": "https://pokeapi.co/api/v2/move/397/"
    }, {
        "name": "poison-jab",
        "url": "https://pokeapi.co/api/v2/move/398/"
    }, {
        "name": "dark-pulse",
        "url": "https://pokeapi.co/api/v2/move/399/"
    }, {
        "name": "night-slash",
        "url": "https://pokeapi.co/api/v2/move/400/"
    }, {
        "name": "aqua-tail",
        "url": "https://pokeapi.co/api/v2/move/401/"
    }, {
        "name": "seed-bomb",
        "url": "https://pokeapi.co/api/v2/move/402/"
    }, {
        "name": "air-slash",
        "url": "https://pokeapi.co/api/v2/move/403/"
    }, {
        "name": "x-scissor",
        "url": "https://pokeapi.co/api/v2/move/404/"
    }, {
        "name": "bug-buzz",
        "url": "https://pokeapi.co/api/v2/move/405/"
    }, {
        "name": "dragon-pulse",
        "url": "https://pokeapi.co/api/v2/move/406/"
    }, {
        "name": "dragon-rush",
        "url": "https://pokeapi.co/api/v2/move/407/"
    }, {
        "name": "power-gem",
        "url": "https://pokeapi.co/api/v2/move/408/"
    }, {
        "name": "drain-punch",
        "url": "https://pokeapi.co/api/v2/move/409/"
    }, {
        "name": "vacuum-wave",
        "url": "https://pokeapi.co/api/v2/move/410/"
    }, {
        "name": "focus-blast",
        "url": "https://pokeapi.co/api/v2/move/411/"
    }, {
        "name": "energy-ball",
        "url": "https://pokeapi.co/api/v2/move/412/"
    }, {
        "name": "brave-bird",
        "url": "https://pokeapi.co/api/v2/move/413/"
    }, {
        "name": "earth-power",
        "url": "https://pokeapi.co/api/v2/move/414/"
    }, {
        "name": "switcheroo",
        "url": "https://pokeapi.co/api/v2/move/415/"
    }, {
        "name": "giga-impact",
        "url": "https://pokeapi.co/api/v2/move/416/"
    }, {
        "name": "nasty-plot",
        "url": "https://pokeapi.co/api/v2/move/417/"
    }, {
        "name": "bullet-punch",
        "url": "https://pokeapi.co/api/v2/move/418/"
    }, {
        "name": "avalanche",
        "url": "https://pokeapi.co/api/v2/move/419/"
    }, {
        "name": "ice-shard",
        "url": "https://pokeapi.co/api/v2/move/420/"
    }, {
        "name": "shadow-claw",
        "url": "https://pokeapi.co/api/v2/move/421/"
    }, {
        "name": "thunder-fang",
        "url": "https://pokeapi.co/api/v2/move/422/"
    }, {
        "name": "ice-fang",
        "url": "https://pokeapi.co/api/v2/move/423/"
    }, {
        "name": "fire-fang",
        "url": "https://pokeapi.co/api/v2/move/424/"
    }, {
        "name": "shadow-sneak",
        "url": "https://pokeapi.co/api/v2/move/425/"
    }, {
        "name": "mud-bomb",
        "url": "https://pokeapi.co/api/v2/move/426/"
    }, {
        "name": "psycho-cut",
        "url": "https://pokeapi.co/api/v2/move/427/"
    }, {
        "name": "zen-headbutt",
        "url": "https://pokeapi.co/api/v2/move/428/"
    }, {
        "name": "mirror-shot",
        "url": "https://pokeapi.co/api/v2/move/429/"
    }, {
        "name": "flash-cannon",
        "url": "https://pokeapi.co/api/v2/move/430/"
    }, {
        "name": "rock-climb",
        "url": "https://pokeapi.co/api/v2/move/431/"
    }, {
        "name": "defog",
        "url": "https://pokeapi.co/api/v2/move/432/"
    }, {
        "name": "trick-room",
        "url": "https://pokeapi.co/api/v2/move/433/"
    }, {
        "name": "draco-meteor",
        "url": "https://pokeapi.co/api/v2/move/434/"
    }, {
        "name": "discharge",
        "url": "https://pokeapi.co/api/v2/move/435/"
    }, {
        "name": "lava-plume",
        "url": "https://pokeapi.co/api/v2/move/436/"
    }, {
        "name": "leaf-storm",
        "url": "https://pokeapi.co/api/v2/move/437/"
    }, {
        "name": "power-whip",
        "url": "https://pokeapi.co/api/v2/move/438/"
    }, {
        "name": "rock-wrecker",
        "url": "https://pokeapi.co/api/v2/move/439/"
    }, {
        "name": "cross-poison",
        "url": "https://pokeapi.co/api/v2/move/440/"
    }, {
        "name": "gunk-shot",
        "url": "https://pokeapi.co/api/v2/move/441/"
    }, {
        "name": "iron-head",
        "url": "https://pokeapi.co/api/v2/move/442/"
    }, {
        "name": "magnet-bomb",
        "url": "https://pokeapi.co/api/v2/move/443/"
    }, {
        "name": "stone-edge",
        "url": "https://pokeapi.co/api/v2/move/444/"
    }, {
        "name": "captivate",
        "url": "https://pokeapi.co/api/v2/move/445/"
    }, {
        "name": "stealth-rock",
        "url": "https://pokeapi.co/api/v2/move/446/"
    }, {
        "name": "grass-knot",
        "url": "https://pokeapi.co/api/v2/move/447/"
    }, {
        "name": "chatter",
        "url": "https://pokeapi.co/api/v2/move/448/"
    }, {
        "name": "judgment",
        "url": "https://pokeapi.co/api/v2/move/449/"
    }, {
        "name": "bug-bite",
        "url": "https://pokeapi.co/api/v2/move/450/"
    }, {
        "name": "charge-beam",
        "url": "https://pokeapi.co/api/v2/move/451/"
    }, {
        "name": "wood-hammer",
        "url": "https://pokeapi.co/api/v2/move/452/"
    }, {
        "name": "aqua-jet",
        "url": "https://pokeapi.co/api/v2/move/453/"
    }, {
        "name": "attack-order",
        "url": "https://pokeapi.co/api/v2/move/454/"
    }, {
        "name": "defend-order",
        "url": "https://pokeapi.co/api/v2/move/455/"
    }, {
        "name": "heal-order",
        "url": "https://pokeapi.co/api/v2/move/456/"
    }, {
        "name": "head-smash",
        "url": "https://pokeapi.co/api/v2/move/457/"
    }, {
        "name": "double-hit",
        "url": "https://pokeapi.co/api/v2/move/458/"
    }, {
        "name": "roar-of-time",
        "url": "https://pokeapi.co/api/v2/move/459/"
    }, {
        "name": "spacial-rend",
        "url": "https://pokeapi.co/api/v2/move/460/"
    }, {
        "name": "lunar-dance",
        "url": "https://pokeapi.co/api/v2/move/461/"
    }, {
        "name": "crush-grip",
        "url": "https://pokeapi.co/api/v2/move/462/"
    }, {
        "name": "magma-storm",
        "url": "https://pokeapi.co/api/v2/move/463/"
    }, {
        "name": "dark-void",
        "url": "https://pokeapi.co/api/v2/move/464/"
    }, {
        "name": "seed-flare",
        "url": "https://pokeapi.co/api/v2/move/465/"
    }, {
        "name": "ominous-wind",
        "url": "https://pokeapi.co/api/v2/move/466/"
    }, {
        "name": "shadow-force",
        "url": "https://pokeapi.co/api/v2/move/467/"
    }],
    "name": "generation-iv",
    "names": [{
        "language": {
            "name": "ja-Hrkt",
            "url": "https://pokeapi.co/api/v2/language/1/"
        },
        "name": "だいよんせだい"
    }, {
        "language": {
            "name": "ko",
            "url": "https://pokeapi.co/api/v2/language/3/"
        },
        "name": "4세대"
    }, {
        "language": {
            "name": "fr",
            "url": "https://pokeapi.co/api/v2/language/5/"
        },
        "name": "Génération IV"
    }, {
        "language": {
            "name": "de",
            "url": "https://pokeapi.co/api/v2/language/6/"
        },
        "name": "Generation IV"
    }, {
        "language": {
            "name": "es",
            "url": "https://pokeapi.co/api/v2/language/7/"
        },
        "name": "Generación IV"
    }, {
        "language": {
            "name": "en",
            "url": "https://pokeapi.co/api/v2/language/9/"
        },
        "name": "Generation IV"
    }, {
        "language": {
            "name": "ja",
            "url": "https://pokeapi.co/api/v2/language/11/"
        },
        "name": "第四世代"
    }],
    "pokemon_species": [{
        "name": "turtwig",
        "url": "https://pokeapi.co/api/v2/pokemon-species/387/"
    }, {
        "name": "chimchar",
        "url": "https://pokeapi.co/api/v2/pokemon-species/390/"
    }, {
        "name": "piplup",
        "url": "https://pokeapi.co/api/v2/pokemon-species/393/"
    }, {
        "name": "starly",
        "url": "https://pokeapi.co/api/v2/pokemon-species/396/"
    }, {
        "name": "bidoof",
        "url": "https://pokeapi.co/api/v2/pokemon-species/399/"
    }, {
        "name": "kricketot",
        "url": "https://pokeapi.co/api/v2/pokemon-species/401/"
    }, {
        "name": "shinx",
        "url": "https://pokeapi.co/api/v2/pokemon-species/403/"
    }, {
        "name": "budew",
        "url": "https://pokeapi.co/api/v2/pokemon-species/406/"
    }, {
        "name": "cranidos",
        "url": "https://pokeapi.co/api/v2/pokemon-species/408/"
    }, {
        "name": "shieldon",
        "url": "https://pokeapi.co/api/v2/pokemon-species/410/"
    }, {
        "name": "burmy",
        "url": "https://pokeapi.co/api/v2/pokemon-species/412/"
    }, {
        "name": "combee",
        "url": "https://pokeapi.co/api/v2/pokemon-species/415/"
    }, {
        "name": "pachirisu",
        "url": "https://pokeapi.co/api/v2/pokemon-species/417/"
    }, {
        "name": "buizel",
        "url": "https://pokeapi.co/api/v2/pokemon-species/418/"
    }, {
        "name": "cherubi",
        "url": "https://pokeapi.co/api/v2/pokemon-species/420/"
    }, {
        "name": "shellos",
        "url": "https://pokeapi.co/api/v2/pokemon-species/422/"
    }, {
        "name": "drifloon",
        "url": "https://pokeapi.co/api/v2/pokemon-species/425/"
    }, {
        "name": "buneary",
        "url": "https://pokeapi.co/api/v2/pokemon-species/427/"
    }, {
        "name": "glameow",
        "url": "https://pokeapi.co/api/v2/pokemon-species/431/"
    }, {
        "name": "chingling",
        "url": "https://pokeapi.co/api/v2/pokemon-species/433/"
    }, {
        "name": "stunky",
        "url": "https://pokeapi.co/api/v2/pokemon-species/434/"
    }, {
        "name": "bronzor",
        "url": "https://pokeapi.co/api/v2/pokemon-species/436/"
    }, {
        "name": "bonsly",
        "url": "https://pokeapi.co/api/v2/pokemon-species/438/"
    }, {
        "name": "mime-jr",
        "url": "https://pokeapi.co/api/v2/pokemon-species/439/"
    }, {
        "name": "happiny",
        "url": "https://pokeapi.co/api/v2/pokemon-species/440/"
    }, {
        "name": "chatot",
        "url": "https://pokeapi.co/api/v2/pokemon-species/441/"
    }, {
        "name": "spiritomb",
        "url": "https://pokeapi.co/api/v2/pokemon-species/442/"
    }, {
        "name": "gible",
        "url": "https://pokeapi.co/api/v2/pokemon-species/443/"
    }, {
        "name": "munchlax",
        "url": "https://pokeapi.co/api/v2/pokemon-species/446/"
    }, {
        "name": "riolu",
        "url": "https://pokeapi.co/api/v2/pokemon-species/447/"
    }, {
        "name": "hippopotas",
        "url": "https://pokeapi.co/api/v2/pokemon-species/449/"
    }, {
        "name": "skorupi",
        "url": "https://pokeapi.co/api/v2/pokemon-species/451/"
    }, {
        "name": "croagunk",
        "url": "https://pokeapi.co/api/v2/pokemon-species/453/"
    }, {
        "name": "grotle",
        "url": "https://pokeapi.co/api/v2/pokemon-species/388/"
    }, {
        "name": "torterra",
        "url": "https://pokeapi.co/api/v2/pokemon-species/389/"
    }, {
        "name": "infernape",
        "url": "https://pokeapi.co/api/v2/pokemon-species/392/"
    }, {
        "name": "prinplup",
        "url": "https://pokeapi.co/api/v2/pokemon-species/394/"
    }, {
        "name": "empoleon",
        "url": "https://pokeapi.co/api/v2/pokemon-species/395/"
    }, {
        "name": "staravia",
        "url": "https://pokeapi.co/api/v2/pokemon-species/397/"
    }, {
        "name": "staraptor",
        "url": "https://pokeapi.co/api/v2/pokemon-species/398/"
    }, {
        "name": "bibarel",
        "url": "https://pokeapi.co/api/v2/pokemon-species/400/"
    }, {
        "name": "kricketune",
        "url": "https://pokeapi.co/api/v2/pokemon-species/402/"
    }, {
        "name": "luxio",
        "url": "https://pokeapi.co/api/v2/pokemon-species/404/"
    }, {
        "name": "luxray",
        "url": "https://pokeapi.co/api/v2/pokemon-species/405/"
    }, {
        "name": "roserade",
        "url": "https://pokeapi.co/api/v2/pokemon-species/407/"
    }, {
        "name": "rampardos",
        "url": "https://pokeapi.co/api/v2/pokemon-species/409/"
    }, {
        "name": "bastiodon",
        "url": "https://pokeapi.co/api/v2/pokemon-species/411/"
    }, {
        "name": "wormadam",
        "url": "https://pokeapi.co/api/v2/pokemon-species/413/"
    }, {
        "name": "mothim",
        "url": "https://pokeapi.co/api/v2/pokemon-species/414/"
    }, {
        "name": "vespiquen",
        "url": "https://pokeapi.co/api/v2/pokemon-species/416/"
    }, {
        "name": "floatzel",
        "url": "https://pokeapi.co/api/v2/pokemon-species/419/"
    }, {
        "name": "cherrim",
        "url": "https://pokeapi.co/api/v2/pokemon-species/421/"
    }, {
        "name": "ambipom",
        "url": "https://pokeapi.co/api/v2/pokemon-species/424/"
    }, {
        "name": "drifblim",
        "url": "https://pokeapi.co/api/v2/pokemon-species/426/"
    }, {
        "name": "lopunny",
        "url": "https://pokeapi.co/api/v2/pokemon-species/428/"
    }, {
        "name": "mismagius",
        "url": "https://pokeapi.co/api/v2/pokemon-species/429/"
    }, {
        "name": "honchkrow",
        "url": "https://pokeapi.co/api/v2/pokemon-species/430/"
    }, {
        "name": "purugly",
        "url": "https://pokeapi.co/api/v2/pokemon-species/432/"
    }, {
        "name": "skuntank",
        "url": "https://pokeapi.co/api/v2/pokemon-species/435/"
    }, {
        "name": "bronzong",
        "url": "https://pokeapi.co/api/v2/pokemon-species/437/"
    }, {
        "name": "gabite",
        "url": "https://pokeapi.co/api/v2/pokemon-species/444/"
    }, {
        "name": "garchomp",
        "url": "https://pokeapi.co/api/v2/pokemon-species/445/"
    }, {
        "name": "lucario",
        "url": "https://pokeapi.co/api/v2/pokemon-species/448/"
    }, {
        "name": "hippowdon",
        "url": "https://pokeapi.co/api/v2/pokemon-species/450/"
    }, {
        "name": "drapion",
        "url": "https://pokeapi.co/api/v2/pokemon-species/452/"
    }, {
        "name": "carnivine",
        "url": "https://pokeapi.co/api/v2/pokemon-species/455/"
    }, {
        "name": "finneon",
        "url": "https://pokeapi.co/api/v2/pokemon-species/456/"
    }, {
        "name": "mantyke",
        "url": "https://pokeapi.co/api/v2/pokemon-species/458/"
    }, {
        "name": "snover",
        "url": "https://pokeapi.co/api/v2/pokemon-species/459/"
    }, {
        "name": "rotom",
        "url": "https://pokeapi.co/api/v2/pokemon-species/479/"
    }, {
        "name": "uxie",
        "url": "https://pokeapi.co/api/v2/pokemon-species/480/"
    }, {
        "name": "mesprit",
        "url": "https://pokeapi.co/api/v2/pokemon-species/481/"
    }, {
        "name": "azelf",
        "url": "https://pokeapi.co/api/v2/pokemon-species/482/"
    }, {
        "name": "dialga",
        "url": "https://pokeapi.co/api/v2/pokemon-species/483/"
    }, {
        "name": "palkia",
        "url": "https://pokeapi.co/api/v2/pokemon-species/484/"
    }, {
        "name": "heatran",
        "url": "https://pokeapi.co/api/v2/pokemon-species/485/"
    }, {
        "name": "regigigas",
        "url": "https://pokeapi.co/api/v2/pokemon-species/486/"
    }, {
        "name": "giratina",
        "url": "https://pokeapi.co/api/v2/pokemon-species/487/"
    }, {
        "name": "cresselia",
        "url": "https://pokeapi.co/api/v2/pokemon-species/488/"
    }, {
        "name": "phione",
        "url": "https://pokeapi.co/api/v2/pokemon-species/489/"
    }, {
        "name": "manaphy",
        "url": "https://pokeapi.co/api/v2/pokemon-species/490/"
    }, {
        "name": "darkrai",
        "url": "https://pokeapi.co/api/v2/pokemon-species/491/"
    }, {
        "name": "shaymin",
        "url": "https://pokeapi.co/api/v2/pokemon-species/492/"
    }, {
        "name": "arceus",
        "url": "https://pokeapi.co/api/v2/pokemon-species/493/"
    }, {
        "name": "lumineon",
        "url": "https://pokeapi.co/api/v2/pokemon-species/457/"
    }, {
        "name": "abomasnow",
        "url": "https://pokeapi.co/api/v2/pokemon-species/460/"
    }, {
        "name": "weavile",
        "url": "https://pokeapi.co/api/v2/pokemon-species/461/"
    }, {
        "name": "magnezone",
        "url": "https://pokeapi.co/api/v2/pokemon-species/462/"
    }, {
        "name": "lickilicky",
        "url": "https://pokeapi.co/api/v2/pokemon-species/463/"
    }, {
        "name": "rhyperior",
        "url": "https://pokeapi.co/api/v2/pokemon-species/464/"
    }, {
        "name": "tangrowth",
        "url": "https://pokeapi.co/api/v2/pokemon-species/465/"
    }, {
        "name": "electivire",
        "url": "https://pokeapi.co/api/v2/pokemon-species/466/"
    }, {
        "name": "magmortar",
        "url": "https://pokeapi.co/api/v2/pokemon-species/467/"
    }, {
        "name": "togekiss",
        "url": "https://pokeapi.co/api/v2/pokemon-species/468/"
    }, {
        "name": "yanmega",
        "url": "https://pokeapi.co/api/v2/pokemon-species/469/"
    }, {
        "name": "leafeon",
        "url": "https://pokeapi.co/api/v2/pokemon-species/470/"
    }, {
        "name": "glaceon",
        "url": "https://pokeapi.co/api/v2/pokemon-species/471/"
    }, {
        "name": "gliscor",
        "url": "https://pokeapi.co/api/v2/pokemon-species/472/"
    }, {
        "name": "porygon-z",
        "url": "https://pokeapi.co/api/v2/pokemon-species/474/"
    }, {
        "name": "gallade",
        "url": "https://pokeapi.co/api/v2/pokemon-species/475/"
    }, {
        "name": "probopass",
        "url": "https://pokeapi.co/api/v2/pokemon-species/476/"
    }, {
        "name": "dusknoir",
        "url": "https://pokeapi.co/api/v2/pokemon-species/477/"
    }, {
        "name": "froslass",
        "url": "https://pokeapi.co/api/v2/pokemon-species/478/"
    }, {
        "name": "monferno",
        "url": "https://pokeapi.co/api/v2/pokemon-species/391/"
    }, {
        "name": "gastrodon",
        "url": "https://pokeapi.co/api/v2/pokemon-species/423/"
    }, {
        "name": "toxicroak",
        "url": "https://pokeapi.co/api/v2/pokemon-species/454/"
    }, {
        "name": "mamoswine",
        "url": "https://pokeapi.co/api/v2/pokemon-species/473/"
    }],
    "types": [],
    "version_groups": [{
        "name": "diamond-pearl",
        "url": "https://pokeapi.co/api/v2/version-group/8/"
    }, {
        "name": "platinum",
        "url": "https://pokeapi.co/api/v2/version-group/9/"
    }, {
        "name": "heartgold-soulsilver",
        "url": "https://pokeapi.co/api/v2/version-group/10/"
    }]
}